metabob/__init__.py
metabob/__main__.py
metabob/_version.py
metabob/core.py
metabob/py.typed
metabob-0.0.1.dist-info/LICENSE
metabob-0.0.1.dist-info/WHEEL
metabob-0.0.1.dist-info/METADATA
metabob-0.0.1.dist-info/RECORD
