Metadata-Version: 2.1
Name: metabob
Version: 0.0.1
Summary: Metabob pkg/cli
Author: jessekrubin
Author-email: jessekrubin@gmail.com
Requires-Python: >=3.6.1,<4.0.0
Classifier: Programming Language :: Python :: 3
Classifier: Programming Language :: Python :: 3.7
Classifier: Programming Language :: Python :: 3.8
Classifier: Programming Language :: Python :: 3.9
